matrad/__init__.py
matrad/properties.py
matrad/utils.py
matrad-0.0.7.dist-info/LICENCE
matrad-0.0.7.dist-info/METADATA
matrad-0.0.7.dist-info/WHEEL
matrad-0.0.7.dist-info/top_level.txt
matrad-0.0.7.dist-info/RECORD
