Metadata-Version: 2.1
Name: matrad
Version: 0.0.7
Summary: A Python interface to the Binance API
Home-page: https://github.com/mancap314/matrad
Author: Manuel Capel
Author-email: manuel.capel82@gmail.com
License: UNKNOWN
Platform: UNKNOWN
Classifier: Programming Language :: Python :: 3
Classifier: License :: OSI Approved :: MIT License
Classifier: Operating System :: OS Independent
Requires-Python: >=3.6
Requires-Dist: requests (>=2.25.1)
